LICENSE
MANIFEST.in
README.rst
setup.cfg
setup.py
django_simple_plugins.egg-info/PKG-INFO
django_simple_plugins.egg-info/SOURCES.txt
django_simple_plugins.egg-info/dependency_links.txt
django_simple_plugins.egg-info/top_level.txt
plugins/__init__.py
plugins/admin.py
plugins/apps.py
plugins/models.py
plugins/urls.py
plugins/views.py
plugins/static/plugins/.DS_Store
plugins/static/plugins/css/codemirror.css
plugins/static/plugins/js/codemirror.js
plugins/static/plugins/js/jQuery-ui.js
plugins/static/plugins/js/jQuery.js
plugins/static/plugins/js/plugins_list.js