Metadata-Version: 1.1
Name: django-simple-plugins
Version: 0.1.4
Summary: A simple yet powerful and configurable tool for adding plugins to your Django project.
Home-page: https://github.com/pistacchio/django-simple-plugins
Author: Gustavo Di Pietro
Author-email: pistacchio@gmail.com
License: MIT License
Platform: UNKNOWN
Classifier: Environment :: Web Environment
Classifier: Framework :: Django
Classifier: Intended Audience :: Developers
Classifier: License :: OSI Approved :: MIT License
Classifier: Operating System :: OS Independent
Classifier: Programming Language :: Python
Classifier: Programming Language :: Python :: 2.7
Classifier: Topic :: Internet :: WWW/HTTP
Classifier: Topic :: Internet :: WWW/HTTP :: Dynamic Content
